ml_experiments/__init__.py
ml_experiments-0.1.3.dist-info/LICENSE
ml_experiments-0.1.3.dist-info/METADATA
ml_experiments-0.1.3.dist-info/WHEEL
ml_experiments-0.1.3.dist-info/top_level.txt
ml_experiments-0.1.3.dist-info/RECORD
