Metadata-Version: 2.1
Name: ml_experiments
Version: 0.1.3
Summary: Monitor you model training anywhere.
Home-page: https://github.com/abdalrhmanu/ml-experiments
Author: ABDELRAHMAN HABIB
Author-email: abdalrhmanusama1@gmail.com
Classifier: Programming Language :: Python :: 3
Classifier: License :: OSI Approved :: MIT License
Classifier: Operating System :: OS Independent
Requires-Python: >=3
License-File: LICENSE
